setup.py
chat_serverside.egg-info/PKG-INFO
chat_serverside.egg-info/SOURCES.txt
chat_serverside.egg-info/dependency_links.txt
chat_serverside.egg-info/requires.txt
chat_serverside.egg-info/top_level.txt
server/__init__.py
server/server.py
server/common/__init__.py
server/common/decos.py
server/common/descrptrs.py
server/common/errors.py
server/common/metaclasses.py
server/common/utils.py
server/common/variables.py
server/logs/__init__.py
server/logs/config_client_log.py
server/logs/config_server_log.py
server/server/__init__.py
server/server/add_user.py
server/server/config_window.py
server/server/core.py
server/server/main_window.py
server/server/remove_user.py
server/server/server_db.py
server/server/stat_window.py