Metadata-Version: 1.0
Name: chat-serverside
Version: 0.0.2
Summary: chat_serverside
Home-page: UNKNOWN
Author: Dmitriy
Author-email: UNKNOWN
License: UNKNOWN
Platform: UNKNOWN
